[
	{ "s": "PACIFIC", "p": [2] },
	{ "s": "PAQ", "p": [2] },
	{ "s": "PARA", "p": [16, 15] },
	{ "s": "PARTE", "p": [6] },
	{ "s": "PARTES", "p": [2] },
	{ "s": "PARÁFRASIS", "p": [2] },
	{ "s": "PASO", "p": [12] },
	{ "s": "PATRIMONIALES", "p": [2] },
	{ "s": "PEGA", "p": [14] },
	{ "s": "PEGAR", "p": [14] },
	{ "s": "PEGAS", "p": [13] },
	{ "s": "PENAL", "p": [2] },
	{ "s": "PENSADO", "p": [2] },
	{ "s": "PERDER", "p": [8] },
	{ "s": "PERMANECEN", "p": [8] },
	{ "s": "PERTENECEN", "p": [12, 2] },
	{ "s": "PERTENEZCA", "p": [2] },
	{ "s": "PESOS", "p": [2] },
	{ "s": "PODER", "p": [2] },
	{ "s": "PODRÁ", "p": [12] },
	{ "s": "PODRÍAN", "p": [8] },
	{ "s": "POR", "p": [2, 7, 5] },
	{ "s": "PORTADA", "p": [2] },
	{ "s": "PORTERIORMENTE", "p": [7] },
	{ "s": "PREFERIDO", "p": [7] },
	{ "s": "PREVIA", "p": [2] },
	{ "s": "PRIMER", "p": [12] },
	{ "s": "PRIMERA", "p": [6] },
	{ "s": "PRINCIPAL", "p": [1] },
	{ "s": "PRIVACIDAD", "p": [2] },
	{ "s": "PRIVILEGIOS", "p": [4] },
	{ "s": "PROBLEMA", "p": [16] },
	{ "s": "PROCESAR", "p": [15, 7] },
	{ "s": "PROCESO", "p": [16, 15, 5] },
	{ "s": "PRODUCCIÓN", "p": [2] },
	{ "s": "PRODUCTOS", "p": [2] },
	{ "s": "PRODUPAQ", "p": [2] },
	{ "s": "PROGRAMA", "p": [2] },
	{ "s": "PROHIBICIÓN", "p": [2] },
	{ "s": "PROHÍBE", "p": [2] },
	{ "s": "PROPIEDAD", "p": [2] },
	{ "s": "PROPÓSITOS", "p": [2] },
	{ "s": "PROTEGIDA", "p": [2] },
	{ "s": "PROTEGIDAS", "p": [2] },
	{ "s": "PROTEGIDOS", "p": [2] },
	{ "s": "PUBLICACIÓN", "p": [2] },
	{ "s": "PUEDE", "p": [7] },
	{ "s": "PUEDES", "p": [16] },
	{ "s": "PYME", "p": [2] },
	{ "s": "PÁGINA", "p": [1] },
	{ "s": "PÚBLICA", "p": [2] }
]